pygerber/.DS_Store
pygerber/__init__.py
pygerber/aperture.py
pygerber/drill_layer.py
pygerber/gerber_layer.py
pygerber/renderers/__init__.py
pygerber/renderers/svg.py
pygerber/standards/__init__.py
pygerber/standards/gerber.py
pygerber/standards/nc_drill.py
python_gerber-0.1.0.dist-info/WHEEL
python_gerber-0.1.0.dist-info/METADATA
python_gerber-0.1.0.dist-info/RECORD
