Metadata-Version: 2.1
Name: python-gerber
Version: 0.1.0
Summary: Python parser for Gerber and NC Drill Files
Author-email: esophagoose <esophagooose@gmail.com>
Classifier: Programming Language :: Python :: 3
Classifier: License :: OSI Approved :: MIT License
Classifier: Operating System :: OS Independent
Requires-Dist: svgwrite==1.4.3
Requires-Dist: pytest>6 ; extra == "test"
Project-URL: Source, https://github.com/esophagoose/python-gerber
Provides-Extra: test
